shiny_cp/__init__.py
shiny_cp/color_picker.py
shiny_cp/distjs/index.js
shiny_cp-0.3.dist-info/METADATA
shiny_cp-0.3.dist-info/WHEEL
shiny_cp-0.3.dist-info/top_level.txt
shiny_cp-0.3.dist-info/RECORD
