Metadata-Version: 2.1
Name: shiny_cp
Version: 0.3
Requires-Dist: shiny>=0.6.0
